mrkdwnify/__init__.py
mrkdwnify-0.1.1.dist-info/METADATA
mrkdwnify-0.1.1.dist-info/WHEEL
mrkdwnify-0.1.1.dist-info/licenses/LICENSE
mrkdwnify-0.1.1.dist-info/RECORD
