Metadata-Version: 2.3
Name: mrkdwnify
Version: 0.1.1
Summary: Python adaptation of the javascript html-to-mrkdwn library.
Project-URL: Homepage, https://github.com/bengelb-io/mrkdwnify
Project-URL: Bug Tracker, https://github.com/bengelb-io/mrkdwnify/issues
Author-email: Benjamin Gelb <benjamin.gelb.io@gmail.com>
License: MIT License
Keywords: converter,html,html-to-mrkdwn,markdown,markdownify,mrkdwn,python
Classifier: Development Status :: 3 - Alpha
Classifier: Intended Audience :: Developers
Classifier: License :: OSI Approved :: MIT License
Classifier: Programming Language :: Python :: 3
Classifier: Programming Language :: Python :: 3.7
Classifier: Programming Language :: Python :: 3.8
Classifier: Programming Language :: Python :: 3.9
Classifier: Programming Language :: Python :: 3.10
Classifier: Programming Language :: Python :: 3.11
Classifier: Topic :: Text Processing :: Markup
Requires-Python: >=3.7
Requires-Dist: markdownify>=0.13.1
Provides-Extra: test
Requires-Dist: pytest>=8.3.3; extra == 'test'
